plomberie/__init__.py
plomberie/exceptions.py
plomberie/manager.py
plomberie/manager_test.py
plomberie/task.py
plomberie/progress_bar/__init__.py
plomberie/progress_bar/abstract_progress_bar.py
plomberie/progress_bar/disabled_progress_bar.py
plomberie/progress_bar/lazy_loaded_progress_bar.py
plomberie-0.0.29.dist-info/LICENSE
plomberie-0.0.29.dist-info/METADATA
plomberie-0.0.29.dist-info/WHEEL
plomberie-0.0.29.dist-info/top_level.txt
plomberie-0.0.29.dist-info/RECORD
